bitbucket2github/__init__.py
bitbucket2github/bitbucket_client.py
bitbucket2github/cli.py
bitbucket2github/github_client.py
bitbucket2github/processor.py
bitbucket2github-1.3.dist-info/METADATA
bitbucket2github-1.3.dist-info/WHEEL
bitbucket2github-1.3.dist-info/entry_points.txt
bitbucket2github-1.3.dist-info/top_level.txt
bitbucket2github-1.3.dist-info/RECORD
