Metadata-Version: 2.1
Name: bitbucket2github
Version: 1.3
Summary: Simple tool to migrate your Bitbucket repositories to GitHub
Home-page: https://github.com/brunogfranca/bitbucket2github
Author: Bruno França
Author-email: bgfranca@gmail.com
License: MIT
Platform: UNKNOWN
Requires-Dist: click (==7.1.1)
Requires-Dist: requests (==2.23.0)
Requires-Dist: PyGithub (==1.47)
